clearskies_gql/__init__.py
clearskies_gql/backends/__init__.py
clearskies_gql/backends/gql_backend.py
clearskies_gql/backends/gql_backend_test.py
clearskies_gql/column_types/__init__.py
clearskies_gql/column_types/connection.py
clear_skies_gql-0.1.2.dist-info/LICENSE
clear_skies_gql-0.1.2.dist-info/METADATA
clear_skies_gql-0.1.2.dist-info/WHEEL
clear_skies_gql-0.1.2.dist-info/top_level.txt
clear_skies_gql-0.1.2.dist-info/RECORD
