Metadata-Version: 2.1
Name: clear-skies-gql
Version: 0.1.2
Summary: clearskies bindings for Apollo GQL
Home-page: https://github.com/cmancone/clearskies-gql
Author: Conor Mancone
Author-email: cmancone@gmail.com
License: MIT
Keywords: setuptools development
Classifier: Development Status :: 4 - Beta
Classifier: Intended Audience :: Developers
Classifier: Topic :: Software Development :: Build Tools
Classifier: License :: OSI Approved :: MIT License
Classifier: Programming Language :: Python :: 3
Requires-Python: >=3.6
License-File: LICENSE
Requires-Dist: clear-skies
